__init__.py
gotrackitdoc/__init__.py
gotrackitdoc/test.py
gotrackitdoc-0.0.2.dist-info/METADATA
gotrackitdoc-0.0.2.dist-info/WHEEL
gotrackitdoc-0.0.2.dist-info/top_level.txt
gotrackitdoc-0.0.2.dist-info/RECORD
