Metadata-Version: 2.1
Name: gotrackitdoc
Version: 0.0.2
Summary: A Python Package test
Author-email: Kai Tang <794568794@qq.com>
License: LICENCE
Project-URL: Homepage, https://github.com/zdsjjtTLG/GoTrackItDoc
Keywords: test
Classifier: Programming Language :: Python :: 3
Classifier: License :: OSI Approved :: MIT License
Classifier: Operating System :: OS Independent
Requires-Python: >=3.8
Requires-Dist: geopandas >=0.14.1
Requires-Dist: shapely
Requires-Dist: networkx
Requires-Dist: pandas
Requires-Dist: numpy
Requires-Dist: keplergl
